CHANGES.txt
DATA_LICENCES.txt
LICENSE.txt
MANIFEST.in
README.txt
requirements.txt
setup.py
apache/apache-wsgi-pip.conf
apache/apache-wsgi.conf
apache/django.wsgi
chimere/__init__.py
chimere/actions.py
chimere/admin.py
chimere/def_settings.py
chimere/feeds.py
chimere/forms.py
chimere/manage.py
chimere/managers.py
chimere/models.py
chimere/runtests.py
chimere/tasks.py
chimere/test_settings.py
chimere/tests.py
chimere/urls.py
chimere/utils.py
chimere/views.py
chimere/widgets.py
chimere.egg-info/PKG-INFO
chimere.egg-info/SOURCES.txt
chimere.egg-info/dependency_links.txt
chimere.egg-info/requires.txt
chimere.egg-info/top_level.txt
chimere/external_utils/OsmApi.py
chimere/external_utils/__init__.py
chimere/fixtures/auth_group.json
chimere/fixtures/default_data.json
chimere/fixtures/initial_data.json
chimere/fixtures/layers-geobretagne.json
chimere/fixtures/layers-opencyclemap.json
chimere/locale/de/LC_MESSAGES/django.po
chimere/locale/fr/LC_MESSAGES/django.po
chimere/management/__init__.py
chimere/management/commands/__init__.py
chimere/management/commands/chimere_export.py
chimere/management/commands/chimere_import.py
chimere/migrations/0001_initial.py
chimere/migrations/0002_rename_models.py
chimere/migrations/0003_auto__add_field_route_submiter_session_key__add_field_route_submiter_e.py
chimere/migrations/0004_auto__add_picturefile__add_multimediafile.py
chimere/migrations/0005_auto__add_multimediatype__add_field_picturefile_order__del_field_multi.py
chimere/migrations/0006_auto__add_importer__add_field_route_import_key__add_field_marker_impor.py
chimere/migrations/0007_auto__add_field_marker_description.py
chimere/migrations/0008_auto__del_field_importer_subcategory__add_field_route_import_source__a.py
chimere/migrations/0009_auto__add_field_importer_state.py
chimere/migrations/0010_auto__add_field_route_import_version__add_field_marker_import_version.py
chimere/migrations/0011_auto__del_field_importer_source_url__add_field_importer_source.py
chimere/migrations/0012_auto__chg_field_picturefile_name__chg_field_multimediafile_url__chg_fi.py
chimere/migrations/0013_auto__add_field_multimediafile_miniature.py
