Metadata-Version: 1.1
Name: chimere
Version: 2.0.3
Summary: Chimere is a kind of online “mashup” which is designed to aggregate geographic data from several sources. Chimere gets a map from OpenStreetMap and display other data added by users. Datas are freely submitted by visitors and then validated by an administrator.
Home-page: http://blog.peacefrogs.net/nim/chimere/
Author: Étienne Loks
Author-email: etienne.loks@peacefrogs.net
License: GPL v3 licence, see COPYING
Platform: UNKNOWN
Classifier: Development Status :: 4 - Beta
Classifier: Environment :: Web Environment
Classifier: Framework :: Django
Classifier: Intended Audience :: Developers
Classifier: Programming Language :: Python
Classifier: Operating System :: OS Independent
